metrics_utility/__init__.py
metrics_utility/exceptions.py
metrics_utility/logger.py
metrics_utility/management_utility.py
metrics_utility/metric_utils.py
metrics_utility/anonymized_rollups/__init__.py
metrics_utility/anonymized_rollups/anonymized_rollups.py
metrics_utility/anonymized_rollups/base_anonymized_rollup.py
metrics_utility/anonymized_rollups/collections.json
metrics_utility/anonymized_rollups/compute_anonymized_rollup.py
metrics_utility/anonymized_rollups/events_modules_anonymized_rollup.py
metrics_utility/anonymized_rollups/execution_environments_anonymized_rollup.py
metrics_utility/anonymized_rollups/helpers.py
metrics_utility/anonymized_rollups/jobhostsummary_anonymized_rollup.py
metrics_utility/anonymized_rollups/jobs_anonymized_rollup.py
metrics_utility/automation_controller_billing/__init__.py
metrics_utility/automation_controller_billing/collector.py
metrics_utility/automation_controller_billing/collectors.py
metrics_utility/automation_controller_billing/helpers.py
metrics_utility/automation_controller_billing/kubernetes_client.py
metrics_utility/automation_controller_billing/prometheus_client.py
metrics_utility/automation_controller_billing/base/__init__.py
metrics_utility/automation_controller_billing/base/s3_handler.py
metrics_utility/automation_controller_billing/dataframe_engine/__init__.py
metrics_utility/automation_controller_billing/dataframe_engine/base.py
metrics_utility/automation_controller_billing/dataframe_engine/dataframe_collection_status.py
metrics_utility/automation_controller_billing/dataframe_engine/dataframe_content_usage.py
metrics_utility/automation_controller_billing/dataframe_engine/dataframe_inventory_scope.py
metrics_utility/automation_controller_billing/dataframe_engine/dataframe_jobhost_summary_usage.py
metrics_utility/automation_controller_billing/dataframe_engine/db_dataframe_host_metric.py
metrics_utility/automation_controller_billing/dataframe_engine/factory.py
metrics_utility-0.7.20260201.dist-info/licenses/LICENSE.md
metrics_utility-0.7.20260201.dist-info/METADATA
metrics_utility-0.7.20260201.dist-info/WHEEL
metrics_utility-0.7.20260201.dist-info/entry_points.txt
metrics_utility-0.7.20260201.dist-info/top_level.txt
metrics_utility-0.7.20260201.dist-info/RECORD
