Metadata-Version: 2.4
Name: metrics-utility
Version: 0.7.20260201
Summary: A metrics utility for Ansible
Author: Red Hat
Author-email: Red Hat <info@ansible.com>
License-Expression: Apache-2.0
Project-URL: Repository, https://github.com/ansible/metrics-utility.git
Project-URL: Issues, https://github.com/ansible/metrics-utility/issues
Project-URL: Changelog, https://github.com/ansible/metrics-utility/blob/devel/CHANGELOG.md
Keywords: ansible,metrics
Classifier: Development Status :: 4 - Beta
Classifier: Intended Audience :: System Administrators
Classifier: Intended Audience :: Developers
Classifier: Operating System :: POSIX
Classifier: Programming Language :: Python :: 3
Classifier: Programming Language :: Python :: 3.12
Classifier: Programming Language :: Python :: 3.13
Classifier: Topic :: System :: Systems Administration
Classifier: Topic :: System :: Monitoring
Classifier: Topic :: Software Development :: Libraries :: Python Modules
Requires-Python: >=3.12
License-File: LICENSE.md
Requires-Dist: boto3==1.35.96
Requires-Dist: botocore==1.35.96
Requires-Dist: distro==1.9.0
Requires-Dist: django==5.2.7
Requires-Dist: kubernetes>=33.1.0
Requires-Dist: openpyxl==3.1.2
Requires-Dist: pandas>=2.2.3
Requires-Dist: psycopg==3.3.0
Requires-Dist: requests==2.32.5
Requires-Dist: segment-analytics-python>=2.3.4
Requires-Dist: setuptools==80.9.0
Dynamic: license-file
